{
  "generated_at": "2026-07-02T02:59:04.583507+00:00",
  "tickers": {
    "EOS": {
      "status": "error",
      "error": "HTTP 402: {\"account_id\":2070286528115322880,\"title\":\"CreditsDepleted\",\"detail\":\"Your enrolled account [2070286528115322880] does not have any credits to fulfill this request.\",\"type\":\"https://api.twitter.com/2/"
    },
    "4DX": {
      "status": "error",
      "error": "HTTP 402: {\"account_id\":2070286528115322880,\"title\":\"CreditsDepleted\",\"detail\":\"Your enrolled account [2070286528115322880] does not have any credits to fulfill this request.\",\"type\":\"https://api.twitter.com/2/"
    },
    "TLX": {
      "status": "error",
      "error": "HTTP 402: {\"account_id\":2070286528115322880,\"title\":\"CreditsDepleted\",\"detail\":\"Your enrolled account [2070286528115322880] does not have any credits to fulfill this request.\",\"type\":\"https://api.twitter.com/2/"
    },
    "DRO": {
      "status": "error",
      "error": "HTTP 402: {\"account_id\":2070286528115322880,\"title\":\"CreditsDepleted\",\"detail\":\"Your enrolled account [2070286528115322880] does not have any credits to fulfill this request.\",\"type\":\"https://api.twitter.com/2/"
    },
    "PLTR": {
      "status": "error",
      "error": "HTTP 402: {\"account_id\":2070286528115322880,\"title\":\"CreditsDepleted\",\"detail\":\"Your enrolled account [2070286528115322880] does not have any credits to fulfill this request.\",\"type\":\"https://api.twitter.com/2/"
    },
    "NVDA": {
      "status": "error",
      "error": "HTTP 402: {\"account_id\":2070286528115322880,\"title\":\"CreditsDepleted\",\"detail\":\"Your enrolled account [2070286528115322880] does not have any credits to fulfill this request.\",\"type\":\"https://api.twitter.com/2/"
    }
  },
  "broad": {},
  "summary": {}
}